celerylog/__init__.py
celerylog/monit.py
celerylog-0.1.0.dist-info/DESCRIPTION.rst
celerylog-0.1.0.dist-info/METADATA
celerylog-0.1.0.dist-info/RECORD
celerylog-0.1.0.dist-info/WHEEL
celerylog-0.1.0.dist-info/metadata.json
celerylog-0.1.0.dist-info/top_level.txt
